_eratosthenes.cpython-312-x86_64-linux-gnu.so
Eratosthenes/__init__.py
Eratosthenes/eratosthenes.py
Eratosthenes-4.0.9.dist-info/LICENSE
Eratosthenes-4.0.9.dist-info/METADATA
Eratosthenes-4.0.9.dist-info/WHEEL
Eratosthenes-4.0.9.dist-info/top_level.txt
Eratosthenes-4.0.9.dist-info/RECORD
