Metadata-Version: 2.1
Name: Eratosthenes
Version: 4.0.9
Summary: Fast prime generation for Python based on Sieve of Eratosthenes
Home-page: https://github.com/vm6502q/Eratosthenes
Author: Dan Strano
Author-email: dan@unitary.fund
License: MIT
Classifier: Environment :: Console
Classifier: Intended Audience :: Developers
Classifier: Intended Audience :: Science/Research
Classifier: Operating System :: POSIX :: Linux
Classifier: Programming Language :: C++
Classifier: Programming Language :: Python :: 3.8
Classifier: Programming Language :: Python :: 3.9
Classifier: Programming Language :: Python :: 3.10
Classifier: Topic :: Scientific/Engineering
License-File: LICENSE
Requires-Dist: pybind11
